roblescarlos/__init__.py
roblescarlos-0.1.dist-info/METADATA
roblescarlos-0.1.dist-info/WHEEL
roblescarlos-0.1.dist-info/top_level.txt
roblescarlos-0.1.dist-info/RECORD
