Metadata-Version: 2.1
Name: roblescarlos
Version: 0.1
Summary: im carlos robles
Home-page: http://github.com/carlosrh18/roblescarlos
Author: Carlos Robles
Author-email: crobles1896@gmail.com
License: MIT
Platform: UNKNOWN
